{
  "/_not-found": "app/_not-found.js",
  "/admin/page": "app/admin/page.js",
  "/admin/vetting/page": "app/admin/vetting/page.js",
  "/login/page": "app/login/page.js",
  "/payment/page": "app/payment/page.js",
  "/register-teacher/page": "app/register-teacher/page.js",
  "/register/page": "app/register/page.js",
  "/search/page": "app/search/page.js",
  "/teachers/[teacherId]/page": "app/teachers/[teacherId]/page.js",
  "/teacher/[teacherId]/premium/page": "app/teacher/[teacherId]/premium/page.js",
  "/(app)/ambassador/page": "app/(app)/ambassador/page.js",
  "/(app)/chat/page": "app/(app)/chat/page.js",
  "/(app)/dashboard-settings/page": "app/(app)/dashboard-settings/page.js",
  "/(app)/dashboard/page": "app/(app)/dashboard/page.js",
  "/(app)/premium-content/page": "app/(app)/premium-content/page.js",
  "/(app)/earnings/page": "app/(app)/earnings/page.js",
  "/(app)/premium-subscription/page": "app/(app)/premium-subscription/page.js",
  "/(app)/profile-builder/page": "app/(app)/profile-builder/page.js",
  "/(app)/profile-edit/page": "app/(app)/profile-edit/page.js",
  "/(app)/progress-reports/page": "app/(app)/progress-reports/page.js",
  "/(app)/progress/page": "app/(app)/progress/page.js",
  "/(app)/vault/create/page": "app/(app)/vault/create/page.js",
  "/(app)/schedule/page": "app/(app)/schedule/page.js",
  "/(app)/vault/page": "app/(app)/vault/page.js",
  "/(app)/welfare-fund/page": "app/(app)/welfare-fund/page.js",
  "/(app)/withdrawals/page": "app/(app)/withdrawals/page.js",
  "/(website)/page": "app/(website)/page.js"
}